Pedersen/pedersen.py
pedersen_commitment_py-0.0.1.dist-info/DESCRIPTION.rst
pedersen_commitment_py-0.0.1.dist-info/METADATA
pedersen_commitment_py-0.0.1.dist-info/RECORD
pedersen_commitment_py-0.0.1.dist-info/WHEEL
pedersen_commitment_py-0.0.1.dist-info/metadata.json
pedersen_commitment_py-0.0.1.dist-info/top_level.txt
